mod26.v
//takes the modulous 26 of an input and outputs that value to final answer matrix?
module mod26#(
    parameter ACC_W = 12, //sum of products width, 12 bits
    parameter DW = 6 // input operand width (INT6)
)(

    input wire [ACC_W-1:0] in, //external input
    output wire [DW-1:0] remainder //external output
);
    // Internal variables for the optimized combinational subtraction loop
    reg [ACC_W+4:0] temp_rem; 
    reg [DW-1:0]    comb_mod26;
    integer         i;

    // Combinational long-division array (Synthesizes to clean subtractor muxes)
    always @(*) begin
        temp_rem = 0;
        
        for (i = ACC_W - 1; i >= 0; i = i - 1) begin
            // Shift left by 1 and pull in the next bit from the input wire
            temp_rem = (temp_rem << 1);
            temp_rem[0] = in[i];
            
            // If the local accumulator hits or exceeds 26, subtract it instantly
            if (temp_rem >= 26) begin
                temp_rem = temp_rem - 26;
            end
        end
        comb_mod26 = temp_rem[DW-1:0];
    end

    assign remainder = comb_mod26; // Directly assign the combinational result to the output

endmodule

mac.v
module mac#(
    parameter DW    = 6,
    parameter ACC_W = 12
)(
    input clk,
    input rst_n,

    input signed [DW-1:0] a,
    input signed [DW-1:0] b,
    input valid_in,
    input clear_acc,

    output reg signed [ACC_W-1:0] acc_out,
    output reg valid_out
);
    reg signed [2*DW-1:0] product;
    reg valid_d;
    reg clear_d;

    always @(posedge clk or negedge rst_n) begin
        if (!rst_n) begin
            product <= 1'b0;
            valid_d <= 1'b0;
            clear_d <= 1'b0;

            acc_out <= 1'b0;
            valid_out <= 1'b0;
        end
        else begin
            //Stage 1 (clock gated)
            valid_d <= valid_in;
            clear_d <= clear_acc;
            //product <= a*b;

            if(valid_in) begin
                product <= a*b; //only updates when valid data is high, also the ony change made
            end

            //Stage 2 (accumulator)
            if (valid_d) begin
                if (clear_d)
                    acc_out <= product;
                else
                    acc_out <= acc_out + product;

                valid_out <= 1'b1;
            end
            else begin
                valid_out <= 1'b0;
            end
        end
    end
endmodule

matmul_top.v
module matmul_mod26_top #(
    parameter N = 2,
    parameter DW = 6,
    parameter ACC_W = $clog2(N * 25 * 25 + 1) + 1,

    parameter KEY_AND_INNER_DIM = N,
    parameter B_COLS = N,

    parameter ADDR_W =
        ((N * B_COLS) <= 1) ? 1 : $clog2(N * B_COLS)
)(
    input wire clk,
    input wire rst_n,

    input wire mode, // 0 = regular key, 1 = inverse key

    input wire start,
    output reg done,

    output wire [
        ((N * KEY_AND_INNER_DIM) <= 1
            ? 1
            : $clog2(N * KEY_AND_INNER_DIM)) - 1 : 0
    ] A_rd_addr,

    output wire [
        ((KEY_AND_INNER_DIM * B_COLS) <= 1
            ? 1
            : $clog2(KEY_AND_INNER_DIM * B_COLS)) - 1 : 0
    ] B_rd_addr,

    input wire signed [DW-1:0] A_rd_data,
    input wire signed [DW-1:0] B_rd_data,

    output wire product_mem_ld_enable,
    output wire [ADDR_W-1:0] product_mem_ld_addr,
    output wire [DW-1:0] product_mem_ld_data
);

    localparam ROW_W =
        (N <= 1) ? 1 : $clog2(N);

    localparam COL_W =
        (B_COLS <= 1) ? 1 : $clog2(B_COLS);

    localparam INNER_W =
        (KEY_AND_INNER_DIM <= 1)
            ? 1
            : $clog2(KEY_AND_INNER_DIM);

    localparam A_ADDR_W =
        ((2 * N * KEY_AND_INNER_DIM) <= 1)
            ? 1
            : $clog2(2 * N * KEY_AND_INNER_DIM);

    localparam B_ADDR_W =
        ((KEY_AND_INNER_DIM * B_COLS) <= 1)
            ? 1
            : $clog2(KEY_AND_INNER_DIM * B_COLS);

    localparam IDLE  = 3'b000;
    localparam FEED  = 3'b001;
    localparam WAIT  = 3'b010;
    localparam WRITE = 3'b011;
    localparam DONE_STATE = 3'b100;

    reg [2:0] current_state;
    reg [2:0] next_state;

    reg [ROW_W-1:0] i;
    reg [COL_W-1:0] j;
    reg [INNER_W-1:0] k;

    reg [ROW_W-1:0] output_i;
    reg [COL_W-1:0] output_j;

    wire [A_ADDR_W-1:0] regular_key_addr;
    wire [B_ADDR_W-1:0] plaintext_addr;

    wire signed [ACC_W-1:0] mac_result;
    wire mac_valid_out;

    wire [DW-1:0] rem_out;

    assign regular_key_addr =
        (i * KEY_AND_INNER_DIM) + k;

    assign plaintext_addr =
        (k * B_COLS) + j;

    // Regular key occupies the first N*N addresses.
    // Inverse key occupies the next N*N addresses.
    assign A_rd_addr = regular_key_addr;

    assign B_rd_addr = plaintext_addr;

    assign product_mem_ld_enable = (current_state == WRITE);

    assign product_mem_ld_addr = (output_i * B_COLS) + output_j;

    assign product_mem_ld_data = rem_out;

    wire mac_valid_in;
    wire mac_clear_acc;

    assign mac_valid_in =
        (current_state == FEED);

    // Clear the accumulator for the first term of each dot product.
    assign mac_clear_acc =
        (current_state == FEED) && (k == 0);

    mac #(
        .DW(DW),
        .ACC_W(ACC_W)
    ) mac_unit (
        .clk       (clk),
        .rst_n     (rst_n),

        .a         (A_rd_data),
        .b         (B_rd_data),
        .valid_in  (mac_valid_in),
        .clear_acc (mac_clear_acc),

        .acc_out   (mac_result),
        .valid_out (mac_valid_out)
    );

    mod26 #(
        .ACC_W(ACC_W),
        .DW(DW)
    ) mod26_unit (
        .in        (mac_result),
        .remainder (rem_out)
    );

    always @(*) begin
        next_state = current_state;

        case (current_state)
            IDLE: begin
                if (start)
                    next_state = FEED;
            end

            FEED: begin
                if (k == KEY_AND_INNER_DIM - 1)
                    next_state = WAIT;
            end

            // Wait one clock so the final product reaches
            // the MAC accumulator.
            WAIT: begin
                next_state = WRITE;
            end

            WRITE: begin
                if ((output_i == N - 1) &&
                    (output_j == B_COLS - 1))
                    next_state = DONE_STATE;
                else
                    next_state = FEED;
            end

            DONE_STATE: begin
                next_state = IDLE;
            end

            default: begin
                next_state = IDLE;
            end
        endcase
    end

    always @(posedge clk or negedge rst_n) begin
        if (!rst_n) begin
            current_state <= IDLE;

            i <= 0;
            j <= 0;
            k <= 0;

            output_i <= 0;
            output_j <= 0;

            done <= 1'b0;
        end
        else begin
            current_state <= next_state;
            done <= 1'b0;

            case (current_state)
                IDLE: begin
                    i <= 0;
                    j <= 0;
                    k <= 0;
                end

                FEED: begin
                    if (k == KEY_AND_INNER_DIM - 1) begin
                        // Save the address of the completed
                        // output matrix element.
                        output_i <= i;
                        output_j <= j;

                        k <= 0;
                    end
                    else begin
                        k <= k + 1'b1;
                    end
                end

                WAIT: begin
                    // The MAC finishes its final accumulation here.
                end

                WRITE: begin
                    // product_mem_ld_enable is high during this state.

                    if (!((output_i == N - 1) &&
                          (output_j == B_COLS - 1))) begin

                        if (j == B_COLS - 1) begin
                            j <= 0;
                            i <= i + 1'b1;
                        end
                        else begin
                            j <= j + 1'b1;
                        end
                    end
                end

                DONE_STATE: begin
                    done <= 1'b1;
                end
            endcase
        end
    end

endmodule

    //A[i][k] B[k][j] = C[i][j]

RTL/testbenches/matmul_top_tb.v
`timescale 1ns/1ps

module matmul_top_tb;

parameter N     = 2;
parameter DW    = 8;
parameter ACC_W = 32;

parameter A_AW = $clog2(2 * N * N);
parameter B_AW = $clog2(N * N);
parameter OUT_AW = $clog2(N * N);

//----------------------------------------------------
// Clock / Reset
//----------------------------------------------------

reg clk;
reg rst_n;
reg start;
reg mode;
wire done;

always #5 clk = ~clk;

//----------------------------------------------------
// DUT <-> "memory" interface
//----------------------------------------------------

// addresses requested by matmul
wire [A_AW-1:0] A_rd_addr;
wire [B_AW-1:0] B_rd_addr;

// data returned to matmul
wire signed [DW-1:0] A_rd_data;
wire signed [DW-1:0] B_rd_data;

// write interface produced by matmul
wire                  product_mem_ld_enable;
wire [OUT_AW-1:0]         product_mem_ld_addr;
wire signed [DW-1:0]  product_mem_ld_data;

//----------------------------------------------------
// "Memory" arrays
//----------------------------------------------------

reg signed [DW-1:0] key_mem [0:2*N*N-1];
reg signed [DW-1:0] plaintext_mem [0:N*N-1];
reg signed [DW-1:0] result_mem    [0:N*N-1];

// asynchronous reads
assign A_rd_data = key_mem[A_rd_addr];
assign B_rd_data = plaintext_mem[B_rd_addr];

// synchronous writes
always @(posedge clk) begin
    if(product_mem_ld_enable)
        result_mem[product_mem_ld_addr] <= product_mem_ld_data;
end

//----------------------------------------------------
// DUT
//----------------------------------------------------

matmul_mod26_top #(
    .N(N),
    .DW(DW),
    .ACC_W(ACC_W)
) dut (
    .clk(clk),
    .rst_n(rst_n),

    .mode(mode),

    .start(start),
    .done(done),

    .A_rd_addr(A_rd_addr),
    .A_rd_data(A_rd_data),

    .B_rd_addr(B_rd_addr),
    .B_rd_data(B_rd_data),

    .product_mem_ld_enable(product_mem_ld_enable),
    .product_mem_ld_addr(product_mem_ld_addr),
    .product_mem_ld_data(product_mem_ld_data)
);

//----------------------------------------------------
// Initialize matrices
//----------------------------------------------------

integer i;

initial begin

    //------------------------------------------------
    // Regular key matrix: addresses 0-3
    //------------------------------------------------

    key_mem[0] = 1;
    key_mem[1] = 22;
    key_mem[2] = 18;
    key_mem[3] = 8;

    //------------------------------------------------
    // Inverse-key space: addresses 4-7
    // Not used because mode = 0 in this test
    //------------------------------------------------

    key_mem[4] = 0;
    key_mem[5] = 0;
    key_mem[6] = 0;
    key_mem[7] = 0;

    //------------------------------------------------
    // Plaintext matrix
    //------------------------------------------------

    plaintext_mem[0] = 0;
    plaintext_mem[1] = 18;
    plaintext_mem[2] = 8;
    plaintext_mem[3] = 2;

    //------------------------------------------------
    // Clear result memory
    //------------------------------------------------

    for (i = 0; i < N*N; i = i + 1)
        result_mem[i] = 0;

end

//----------------------------------------------------
// Test
//----------------------------------------------------

integer r,c;

initial begin

    $dumpvars(0,matmul_top_tb);

    clk   = 0;
    rst_n = 0;
    start = 0;
    mode = 0;

    repeat(3) @(posedge clk);

    rst_n = 1;

    @(negedge clk);
    start = 1;

    @(negedge clk);
    start = 0;

    wait(done);

    @(posedge clk);

    $display("\nResult matrix:");

    for(r=0;r<N;r=r+1) begin
        for(c=0;c<N;c=c+1)
            $write("%6d ", result_mem[r*N+c]);
        $write("\n");
    end

    $finish;

end

endmodule

_build/default/testbenches/matmul_top_tb.vcd
$date
	Thu Jul 30 00:07:34 2026
$end
$version
	Icarus Verilog
$end
$timescale
	1ps
$end
$scope module matmul_top_tb $end
$var wire 8 ! A_rd_data [7:0] $end
$var wire 8 " B_rd_data [7:0] $end
$var wire 1 # product_mem_ld_enable $end
$var wire 8 $ product_mem_ld_data [7:0] $end
$var wire 2 % product_mem_ld_addr [1:0] $end
$var wire 1 & done $end
$var wire 2 ' B_rd_addr [1:0] $end
$var wire 3 ( A_rd_addr [2:0] $end
$var parameter 32 ) ACC_W $end
$var parameter 32 * A_AW $end
$var parameter 32 + B_AW $end
$var parameter 32 , DW $end
$var parameter 32 - N $end
$var parameter 32 . OUT_AW $end
$var reg 1 / clk $end
$var reg 1 0 mode $end
$var reg 1 1 rst_n $end
$var reg 1 2 start $end
$var integer 32 3 c [31:0] $end
$var integer 32 4 i [31:0] $end
$var integer 32 5 r [31:0] $end
$scope module dut $end
$var wire 8 6 A_rd_data [7:0] $end
$var wire 2 7 B_rd_addr [1:0] $end
$var wire 8 8 B_rd_data [7:0] $end
$var wire 1 / clk $end
$var wire 1 9 mac_clear_acc $end
$var wire 1 0 mode $end
$var wire 8 : product_mem_ld_data [7:0] $end
$var wire 1 1 rst_n $end
$var wire 1 2 start $end
$var wire 8 ; rem_out [7:0] $end
$var wire 3 < regular_key_addr [2:0] $end
$var wire 1 # product_mem_ld_enable $end
$var wire 2 = product_mem_ld_addr [1:0] $end
$var wire 2 > plaintext_addr [1:0] $end
$var wire 1 ? mac_valid_out $end
$var wire 1 @ mac_valid_in $end
$var wire 32 A mac_result [31:0] $end
$var wire 2 B A_rd_addr [1:0] $end
$var parameter 32 C ACC_W $end
$var parameter 32 D ADDR_W $end
$var parameter 32 E A_ADDR_W $end
$var parameter 32 F B_ADDR_W $end
$var parameter 32 G B_COLS $end
$var parameter 32 H COL_W $end
$var parameter 3 I DONE_STATE $end
$var parameter 32 J DW $end
$var parameter 3 K FEED $end
$var parameter 3 L IDLE $end
$var parameter 32 M INNER_W $end
$var parameter 32 N KEY_AND_INNER_DIM $end
$var parameter 32 O N $end
$var parameter 32 P ROW_W $end
$var parameter 3 Q WAIT $end
$var parameter 3 R WRITE $end
$var reg 3 S current_state [2:0] $end
$var reg 1 & done $end
$var reg 1 T i $end
$var reg 1 U j $end
$var reg 1 V k $end
$var reg 3 W next_state [2:0] $end
$var reg 1 X output_i $end
$var reg 1 Y output_j $end
$scope module mac_unit $end
$var wire 8 Z a [7:0] $end
$var wire 8 [ b [7:0] $end
$var wire 1 9 clear_acc $end
$var wire 1 / clk $end
$var wire 1 1 rst_n $end
$var wire 1 @ valid_in $end
$var parameter 32 \ ACC_W $end
$var parameter 32 ] DW $end
$var reg 32 ^ acc_out [31:0] $end
$var reg 1 _ clear_d $end
$var reg 16 ` product [15:0] $end
$var reg 1 a valid_d $end
$var reg 1 ? valid_out $end
$upscope $end
$scope module mod26_unit $end
$var wire 32 b in [31:0] $end
$var wire 8 c remainder [7:0] $end
$var parameter 32 d ACC_W $end
$var parameter 32 e DW $end
$var reg 8 f comb_mod26 [7:0] $end
$var reg 37 g temp_rem [36:0] $end
$var integer 32 h i [31:0] $end
$upscope $end
$upscope $end
$upscope $end
$enddefinitions $end
$comment Show the parameter values. $end
$dumpall
b1000 e
b100000 d
b1000 ]
b100000 \
b11 R
b10 Q
b1 P
b10 O
b10 N
b1 M
b0 L
b1 K
b1000 J
b100 I
b1 H
b10 G
b10 F
b11 E
b10 D
b100000 C
b10 .
b10 -
b1000 ,
b10 +
b11 *
b100000 )
$end
#0
$dumpvars
b11111111111111111111111111111111 h
b0 g
b0 f
b0 c
b0 b
0a
b0 `
0_
b0 ^
b0 [
b1 Z
0Y
0X
b0 W
0V
0U
0T
b0 S
b0 B
b0 A
0@
0?
b0 >
b0 =
b0 <
b0 ;
b0 :
09
b0 8
b0 7
b1 6
bx 5
b100 4
bx 3
02
01
00
0/
b0 (
b0 '
0&
b0 %
b0 $
0#
b0 "
b1 !
$end
#5000
1/
#10000
0/
#15000
1/
#20000
0/
#25000
11
1/
#30000
b1 W
12
0/
#35000
19
1@
b1 S
1/
#40000
02
0/
#45000
b10110 !
b10110 6
b10110 Z
b1 (
b1 B
b1000 "
b1000 8
b1000 [
b1 <
b10 '
b10 7
b10 >
09
b10 W
1V
1_
1a
1/
#50000
0/
#55000
b1 !
b1 6
b1 Z
b0 (
b0 B
b0 "
b0 8
b0 [
b0 <
b0 '
b0 7
b0 >
b11 W
1?
b10110000 `
0_
0V
0@
b10 S
1/
#60000
0/
#65000
b1 W
b10100 $
b10100 :
b10100 ;
b10100 c
b10100 f
b10100 g
b11111111111111111111111111111111 h
1#
b11 S
b10110000 A
b10110000 ^
b10110000 b
0a
1/
#70000
0/
#75000
b10010 "
b10010 8
b10010 [
b1 '
b1 7
b1 >
19
0?
1U
0#
1@
b1 S
1/
#80000
0/
#85000
b10110 !
b10110 6
b10110 Z
b1 (
b1 B
b10 "
b10 8
b10 [
b1 <
b11 '
b11 7
b11 >
09
b10 W
1V
b10010 `
1_
1a
1/
#90000
0/
#95000
b1 !
b1 6
b1 Z
b0 (
b0 B
b10010 "
b10010 8
b10010 [
b0 <
b1 '
b1 7
b1 >
b1 %
b1 =
b10010 $
b10010 :
b10010 ;
b10010 c
b10010 f
b11111111111111111111111111111111 h
b10010 g
b11 W
1?
b10010 A
b10010 ^
b10010 b
b101100 `
0_
0V
1Y
0@
b10 S
1/
#100000
0/
#105000
b1 W
b1010 $
b1010 :
b1010 ;
b1010 c
b1010 f
b11111111111111111111111111111111 h
b1010 g
1#
b11 S
b111110 A
b111110 ^
b111110 b
0a
1/
#110000
0/
#115000
b10010 !
b10010 6
b10010 Z
b10 (
b10 B
b0 "
b0 8
b0 [
b10 <
b0 '
b0 7
b0 >
19
0?
1T
0U
0#
1@
b1 S
1/
#120000
0/
#125000
b1000 !
b1000 6
b1000 Z
b11 (
b11 B
b1000 "
b1000 8
b1000 [
b11 <
b10 '
b10 7
b10 >
09
b10 W
1V
b0 `
1_
1a
1/
#130000
0/
#135000
b10010 !
b10010 6
b10010 Z
b10 (
b10 B
b0 "
b0 8
b0 [
b10 <
b0 '
b0 7
b0 >
b10 %
b10 =
b0 $
b0 :
b0 ;
b0 c
b0 f
b11111111111111111111111111111111 h
b0 g
b11 W
1?
b0 A
b0 ^
b0 b
b1000000 `
0_
0V
0Y
1X
0@
b10 S
1/
#140000
0/
#145000
b1 W
b1100 $
b1100 :
b1100 ;
b1100 c
b1100 f
b1100 g
b11111111111111111111111111111111 h
1#
b11 S
b1000000 A
b1000000 ^
b1000000 b
0a
1/
#150000
0/
#155000
b10010 "
b10010 8
b10010 [
b1 '
b1 7
b1 >
19
0?
1U
0#
1@
b1 S
1/
#160000
0/
#165000
b1000 !
b1000 6
b1000 Z
b11 (
b11 B
b10 "
b10 8
b10 [
b11 <
b11 '
b11 7
b11 >
09
b10 W
1V
b101000100 `
1_
1a
1/
#170000
0/
#175000
b10010 !
b10010 6
b10010 Z
b10 (
b10 B
b10010 "
b10010 8
b10010 [
b10 <
b1 '
b1 7
b1 >
b11 %
b11 =
b11111111111111111111111111111111 h
b1100 g
b11 W
1?
b101000100 A
b101000100 ^
b101000100 b
b10000 `
0_
0V
1Y
0@
b10 S
1/
#180000
0/
#185000
b100 W
b10 $
b10 :
b10 ;
b10 c
b10 f
b11111111111111111111111111111111 h
b10 g
1#
b11 S
b101010100 A
b101010100 ^
b101010100 b
0a
1/
#190000
0/
#195000
b0 W
0?
0#
b100 S
1/
#200000
0/
#205000
1&
b0 S
1/
#210000
0/
#215000
b1 !
b1 6
b1 Z
b0 (
b0 "
b0 8
b0 [
b0 B
b0 '
b0 7
b0 >
b0 <
0U
0T
0&
b10 3
b10 5
1/
